ufload/__init__.py
ufload/cloud.py
ufload/db.py
ufload/httpfile.py
ufload/test_cloud.py
ufload/test_db.py
ufload/webdav.py
ufload/cli/__init__.py
ufload/cli/main.py
ufload/cli/test_main.py
ufload-0.281.dist-info/LICENSE
ufload-0.281.dist-info/METADATA
ufload-0.281.dist-info/WHEEL
ufload-0.281.dist-info/entry_points.txt
ufload-0.281.dist-info/top_level.txt
ufload-0.281.dist-info/RECORD
