Metadata-Version: 2.1
Name: ufload
Version: 0.281
Summary: Unifield loader
Home-page: http://www.msf.org/
Author: MSF
Author-email: UNKNOWN
License: MIT License
Download-URL: https://github.com/Unifield/ufload/tarball/0.281
Platform: UNKNOWN
Classifier: Development Status :: 3 - Alpha
Classifier: Environment :: Console
Classifier: Intended Audience :: Customer Service
Classifier: License :: OSI Approved :: MIT License
Classifier: Programming Language :: Python :: 2
Classifier: Programming Language :: Python :: 2.7
Requires-Python: >=2.7
Requires-Dist: pyOpenSSL (==19.1.0)
Requires-Dist: ndg-httpsclient (==0.5.1)
Requires-Dist: pyasn1 (==0.4.8)
Requires-Dist: easywebdav (==1.2.0)
Requires-Dist: oerplib (==0.8.4)
Requires-Dist: pybase64 (==0.5.0)
Requires-Dist: Office365-REST-Python-Client (==2.1.5)
